polydata/__init__.py
polydata/math/__init__.py
polydata/math/array.py
polydata/math/arraysetops.py
polydata/math/graph.py
polydata/math/hist.py
polydata/math/jaggedarray.py
polydata/math/numint.py
polydata/math/function/__init__.py
polydata/math/function/constraint.py
polydata/math/function/function.py
polydata/math/function/functions.py
polydata/math/function/meta.py
polydata/math/function/relation.py
polydata/math/function/testfunction.py
polydata/math/linalg/__init__.py
polydata/math/linalg/_solve.py
polydata/math/linalg/_tensop.py
polydata/math/linalg/array.py
polydata/math/linalg/csys.py
polydata/math/linalg/frame.py
polydata/math/linalg/linalg.py
polydata/math/linalg/tensor.py
polydata/math/linalg/vector.py
polydata/math/linalg/frontal/__init__.py
polydata/math/linalg/frontal/frontal.py
polydata/math/linalg/frontal/frutils.py
polydata/math/linalg/frontal/path.py
polydata/math/linalg/frontal/postproc.py
polydata/math/linalg/frontal/proc.py
polydata/math/linalg/frontal/topo.py
polydata/math/linalg/sparse/__init__.py
polydata/math/linalg/sparse/csr.py
polydata/math/linalg/sparse/utils.py
polydata/math/optimize/__init__.py
polydata/math/optimize/genetic.py
polydata/math/optimize/lp.py
polydata/mesh/H27.py
polydata/mesh/H8.py
polydata/mesh/Q4.py
polydata/mesh/Q9.py
polydata/mesh/T3.py
polydata/mesh/T6.py
polydata/mesh/__init__.py
polydata/mesh/cell.py
polydata/mesh/celldata.py
polydata/mesh/frame.py
polydata/mesh/line.py
polydata/mesh/polydata.py
polydata/mesh/polygon.py
polydata/mesh/polyhedron.py
polydata/mesh/pop.py
polydata/mesh/rgrid.py
polydata/mesh/tile.py
polydata/mesh/utils.py
polydata/mesh/vtkcelltypes.py
polydata/mesh/vtkutils.py
polydata/mesh/topo/__init__.py
polydata/mesh/topo/topo.py
polydata/mesh/topo/topodata.py
polydata/mesh/topo/tr.py
polydata/mesh/tri/__init__.py
polydata/mesh/tri/trimesh.py
polydata/mesh/tri/triplot.py
polydata/mesh/tri/triutils.py
polydata/tools/__init__.py
polydata/tools/clipboard.py
polydata/tools/file.py
polydata-0.0.1.dist-info/LICENSE
polydata-0.0.1.dist-info/METADATA
polydata-0.0.1.dist-info/WHEEL
polydata-0.0.1.dist-info/top_level.txt
polydata-0.0.1.dist-info/RECORD
